<?xml version="1.0" encoding="UTF-8"?>
<actor PGFVersion="0.25" id="id134994" GSCVersion="1.25.95"><attributes><text id="name">enemy</text><real id="time">0</real><point id="position"><real id="x">0</real><real id="y">0</real></point><size id="size"><real id="width">40</real><real id="height">40</real></size><angle id="rotation">0</angle><color id="color"><real id="red">0.99999928474426</real><real id="green">0.99997442960739</real><real id="blue">0.99999129772186</real><real id="alpha">1</real></color><image id="image">Enemy_patrolling</image><text id="tags"></text><boolean id="preloadArt">true</boolean><integer name="AttackRange" id="id180089">100</integer><boolean name="PlayerToRight" id="id710088">false</boolean><real name="MinTime" id="id838451">0.5</real><real name="MaxTime" id="id952933">2</real><boolean name="IsAttacking" id="id642039">false</boolean><integer name="distance" id="id904887">0</integer></attributes><behaviors><behavior id="id580425" class="TimerBehavior" enabled="true"><attributes><text id="name">set distance every frame</text><text id="bundleName">Timer.behavior</text><boolean id="runOnce">false</boolean><boolean id="runSequentially">false</boolean><index id="timerType">0</index><real id="interval">0</real><boolean id="runToCompletion">false</boolean></attributes><behaviors><behavior id="id285272" class="ChangeAttributeAction" enabled="true"><attributes><text id="name">set</text><text id="bundleName">ChangeAttribute.behavior</text><text id="targetAttribute">self.attributes.id904887</text><text id="RHS"><expression><reference keypath="self.attributes.position.x"/><string xml:space="preserve">-</string><reference keypath="game.attributes.id902649"/></expression></text></attributes></behavior></behaviors></behavior><behavior id="id601486" class="AccelerateBehavior" enabled="true"><attributes><text id="name">gravity</text><text id="bundleName">Accelerate.behavior</text><angle id="direction">270</angle><index id="space">0</index><real id="acceleration">600</real></attributes></behavior><behavior id="id835241" class="CompoundBehavior" enabled="true"><attributes><text id="name">collides</text><text id="bundleName">Group.behavior</text><boolean id="runOnce">false</boolean><boolean id="runSequentially">false</boolean></attributes><behaviors><behavior id="id410487" class="CollideBehavior" enabled="true"><attributes><text id="name">collide with charcacter</text><text id="bundleName">Collide.behavior</text><text id="prototypeKey">id765552</text><text id="actorTag">Ground</text><index id="mode">0</index></attributes></behavior><behavior id="id120430" class="CollideBehavior" enabled="true"><attributes><text id="name">collide with ground</text><text id="bundleName">Collide.behavior</text><text id="prototypeKey">id485765</text><text id="actorTag">Ground</text><index id="mode">1</index></attributes></behavior></behaviors></behavior><behavior enabled="true" id="id226069" class="RuleBehavior"><attributes><text id="name">Attack range</text><text id="bundleName">Rule.behavior</text><boolean id="runOnce">false</boolean><boolean id="runSequentially">false</boolean><real id="compoundConditionKind">0</real></attributes><conditions><condition pluginPredicateTypeIndex="0" id="id281164" eventType="mouse position"><attributes><index id="conditionType">2</index><text id="subjectAttribute">self.attributes.position.x</text></attributes><predicate type="number"><attributes><text id="operator">&lt;=</text><real id="RHS"><expression><reference keypath="self.attributes.id180089"/></expression></real></attributes></predicate><subjectPredicate type="number"><attributes><text id="operator">=</text><real id="RHS"><expression><string xml:space="preserve">abs(</string><reference keypath="self.attributes.position.x"/><string xml:space="preserve">-</string><reference keypath="game.attributes.id902649"/><string xml:space="preserve">)</string></expression></real></attributes></subjectPredicate></condition><condition id="id372555" pluginPredicateTypeIndex="0" eventType="mouse position"><attributes><index id="conditionType">1</index><text id="subjectAttribute">game.attributes.id580978</text></attributes><predicate type="boolean"><attributes><index id="RHS">0</index></attributes></predicate></condition><condition id="id252382" pluginPredicateTypeIndex="0" eventType="mouse position"><attributes><index id="conditionType">1</index><text id="subjectAttribute">game.attributes.id571925</text></attributes><predicate type="number"><attributes><text id="operator">=</text><real id="RHS"><expression><reference keypath="self.attributes.position.y"/></expression></real></attributes></predicate></condition></conditions><behaviors><behavior id="id133409" class="TimerBehavior" enabled="true"><attributes><text id="name">Timer</text><text id="bundleName">Timer.behavior</text><boolean id="runOnce">false</boolean><boolean id="runSequentially">false</boolean><index id="timerType">1</index><real id="interval"><expression><string xml:space="preserve">random(</string><reference keypath="self.attributes.id838451"/><string xml:space="preserve">,</string><reference keypath="self.attributes.id952933"/><string xml:space="preserve">)</string></expression></real><boolean id="runToCompletion">false</boolean></attributes><behaviors><behavior id="id905853" class="ChangeAttributeAction" enabled="true"><attributes><text id="name">attack trigger</text><text id="bundleName">ChangeAttribute.behavior</text><text id="targetAttribute">self.attributes.id642039</text><text id="RHS">true</text></attributes></behavior></behaviors></behavior></behaviors><elseBehaviors><behavior id="id458293" class="ChangeAttributeAction" enabled="true"><attributes><text id="name">attack trigger</text><text id="bundleName">ChangeAttribute.behavior</text><text id="targetAttribute">self.attributes.id642039</text><text id="RHS">false</text></attributes></behavior></elseBehaviors></behavior><behavior enabled="true" id="id493268" class="RuleBehavior"><attributes><text id="name">Attack</text><text id="bundleName">Rule.behavior</text><boolean id="runOnce">false</boolean><boolean id="runSequentially">false</boolean><real id="compoundConditionKind">0</real></attributes><conditions><condition id="id766656" pluginPredicateTypeIndex="0" eventType="mouse position"><attributes><index id="conditionType">1</index><text id="subjectAttribute">self.attributes.id642039</text></attributes><predicate type="boolean"><attributes><index id="RHS">1</index></attributes></predicate></condition></conditions><behaviors><behavior id="id751897" class="AnimateBehavior" enabled="true"><attributes><text id="name">attack animation</text><text id="bundleName">Animate.behavior</text><text id="images">Enemy_fight</text><index id="speed">1</index><boolean id="loop">true</boolean><boolean id="restoreActorImage">true</boolean><text id="currentFrameAttribute"></text></attributes></behavior><behavior id="id856037" class="TimerBehavior" enabled="true"><attributes><text id="name">attack time</text><text id="bundleName">Timer.behavior</text><boolean id="runOnce">false</boolean><boolean id="runSequentially">false</boolean><index id="timerType">1</index><real id="interval">1</real><boolean id="runToCompletion">false</boolean></attributes><behaviors><behavior id="id722782" class="ChangeAttributeAction" enabled="true"><attributes><text id="name">Change damage bool</text><text id="bundleName">ChangeAttribute.behavior</text><text id="targetAttribute">game.attributes.id580978</text><text id="RHS">1</text></attributes></behavior></behaviors></behavior></behaviors><elseBehaviors/></behavior><behavior enabled="true" id="id244395" class="RuleBehavior"><attributes><text id="name">chase to attack</text><text id="bundleName">Rule.behavior</text><boolean id="runOnce">false</boolean><boolean id="runSequentially">false</boolean><real id="compoundConditionKind">0</real></attributes><conditions><condition pluginPredicateTypeIndex="0" id="id677000" eventType="mouse position"><attributes><index id="conditionType">2</index></attributes><predicate type="number"><attributes><text id="operator">&lt;</text><real id="RHS">200</real></attributes></predicate><subjectPredicate type="number"><attributes><text id="operator">=</text><real id="RHS"><expression><string xml:space="preserve">abs(</string><reference keypath="self.attributes.id904887"/><string xml:space="preserve">)</string></expression></real></attributes></subjectPredicate></condition><condition pluginPredicateTypeIndex="0" id="id544724" eventType="mouse position"><attributes><index id="conditionType">2</index></attributes><predicate type="number"><attributes><text id="operator">&gt;</text><real id="RHS">30</real></attributes></predicate><subjectPredicate type="number"><attributes><text id="operator">=</text><real id="RHS"><expression><string xml:space="preserve">abs(</string><reference keypath="self.attributes.id904887"/><string xml:space="preserve">)</string></expression></real></attributes></subjectPredicate></condition></conditions><behaviors><behavior id="id806017" class="AnimateBehavior" enabled="true"><attributes><text id="name">Animate attack</text><text id="bundleName">Animate.behavior</text><text id="images">Enemy_patrolling</text><index id="speed">1</index><boolean id="loop">true</boolean><boolean id="restoreActorImage">true</boolean><text id="currentFrameAttribute"></text></attributes></behavior><behavior id="id597937" class="MoveToBehavior" enabled="true"><attributes><text id="name">Move to character</text><text id="bundleName">MoveTo.behavior</text><boolean id="runToCompletion">false</boolean><point id="position"><real id="x"><expression><reference keypath="game.attributes.id902649"/></expression></real><real id="y"><expression><string xml:space="preserve">0</string></expression></real></point><index id="space">1</index><real id="speed"><expression><reference keypath="game.attributes.id887397"/></expression></real></attributes></behavior></behaviors><elseBehaviors/></behavior><behavior enabled="true" id="id870852" class="RuleBehavior"><attributes><text id="name">flip depending on neg/pos distance</text><text id="bundleName">Rule.behavior</text><boolean id="runOnce">false</boolean><boolean id="runSequentially">false</boolean><real id="compoundConditionKind">0</real></attributes><conditions><condition id="id195845" pluginPredicateTypeIndex="0" eventType="mouse position"><attributes><index id="conditionType">1</index><text id="subjectAttribute">self.attributes.id904887</text></attributes><predicate type="number"><attributes><text id="operator">&lt;=</text><real id="RHS">0</real></attributes></predicate></condition></conditions><behaviors><behavior id="id685066" class="ChangeAttributeAction" enabled="true"><attributes><text id="name">flip dat boi</text><text id="bundleName">ChangeAttribute.behavior</text><text id="targetAttribute">self.aspects.graphics.attributes.flipHorizontally</text><text id="RHS">true</text></attributes></behavior></behaviors><elseBehaviors><behavior id="id691741" class="ChangeAttributeAction" enabled="true"><attributes><text id="name">flip dat boi again</text><text id="bundleName">ChangeAttribute.behavior</text><text id="targetAttribute">self.aspects.graphics.attributes.flipHorizontally</text><text id="RHS">false</text></attributes></behavior></elseBehaviors></behavior></behaviors><aspects><graphics><attributes><boolean id="visible">true</boolean><enumeration id="blendingMode">0</enumeration><enumeration id="horizontalWrap">0</enumeration><enumeration id="verticalWrap">0</enumeration><enumeration id="horizontalAnchor">0</enumeration><enumeration id="verticalAnchor">0</enumeration><boolean id="flipHorizontally">false</boolean><boolean id="flipVertically">false</boolean><integer id="tileWidth">40</integer><integer id="tileHeight">40</integer></attributes></graphics><motion><attributes><point id="linearVelocity"><real id="x">0</real><real id="y">0</real></point><point id="centerOfMass"><real id="x">0</real><real id="y">0</real></point><real id="angularVelocity">0</real><real id="maxSpeed">0</real><boolean id="applyMaxSpeed">false</boolean><boolean id="pin">false</boolean></attributes></motion><physics><attributes><real id="density">100</real><real id="friction">0</real><real id="restitution">0</real><boolean id="fixedRotation">true</boolean><boolean id="movable">true</boolean><enumeration id="collisionShape">0</enumeration><real id="drag">0</real><real id="angularDrag">0</real><boolean id="canSleep">true</boolean><boolean id="betterColisions">false</boolean></attributes></physics></aspects></actor>
